sonetsim/__init__.py
sonetsim/sonetsim.py
sonetsim/tests/__init__.py
sonetsim/tests/simulator_validator.py
sonetsim-1.0.0.dist-info/LICENSE
sonetsim-1.0.0.dist-info/METADATA
sonetsim-1.0.0.dist-info/WHEEL
sonetsim-1.0.0.dist-info/RECORD
